rmsdynautomationtool/.env
rmsdynautomationtool/DISCLAIMER
rmsdynautomationtool/EULA
rmsdynautomationtool/__init__.py
rmsdynautomationtool/global_executor.cp39-win_amd64.pyd
rmsdynautomationtool/plot/__init__.py
rmsdynautomationtool/plot/plot_color_schemes.cp39-win_amd64.pyd
rmsdynautomationtool/plot/plot_data_intersections.cp39-win_amd64.pyd
rmsdynautomationtool/plot/plot_driver.cp39-win_amd64.pyd
rmsdynautomationtool/plot/plot_filename_generator.cp39-win_amd64.pyd
rmsdynautomationtool/plot/plot_input_config.cp39-win_amd64.pyd
rmsdynautomationtool/plot/plot_launcher.py
rmsdynautomationtool/plot/plot_legend_parser.cp39-win_amd64.pyd
rmsdynautomationtool/plot/plot_methods.cp39-win_amd64.pyd
rmsdynautomationtool/plot/plot_page_defaults.cp39-win_amd64.pyd
rmsdynautomationtool/plot/plot_subplot_defaults.cp39-win_amd64.pyd
rmsdynautomationtool/plot/plot_table_generator.cp39-win_amd64.pyd
rmsdynautomationtool/shared/__init__.py
rmsdynautomationtool/shared/base_classes.cp39-win_amd64.pyd
rmsdynautomationtool/shared/case_mapping_utils.cp39-win_amd64.pyd
rmsdynautomationtool/shared/config_loader.cp39-win_amd64.pyd
rmsdynautomationtool/shared/configure.cp39-win_amd64.pyd
rmsdynautomationtool/shared/engine_inputs.cp39-win_amd64.pyd
rmsdynautomationtool/shared/excel_csv_reader.cp39-win_amd64.pyd
rmsdynautomationtool/shared/global_definitions.cp39-win_amd64.pyd
rmsdynautomationtool/shared/input_data_models.cp39-win_amd64.pyd
rmsdynautomationtool/shared/input_object_parser.cp39-win_amd64.pyd
rmsdynautomationtool/simulate/__init__.py
rmsdynautomationtool/simulate/sim_case_summary_display.cp39-win_amd64.pyd
rmsdynautomationtool/simulate/sim_driver.cp39-win_amd64.pyd
rmsdynautomationtool/simulate/sim_engine_wrapper.cp39-win_amd64.pyd
rmsdynautomationtool/simulate/sim_launcher.py
rmsdynautomationtool/simulate/sim_precalc_engine.cp39-win_amd64.pyd
rmsdynautomationtool-0.0.1.dev1.dist-info/licenses/LICENSE
rmsdynautomationtool-0.0.1.dev1.dist-info/METADATA
rmsdynautomationtool-0.0.1.dev1.dist-info/WHEEL
rmsdynautomationtool-0.0.1.dev1.dist-info/top_level.txt
rmsdynautomationtool-0.0.1.dev1.dist-info/RECORD
