Metadata-Version: 2.4
Name: rmsdynautomationtool
Version: 0.0.1.dev1
Summary: This package is useful for PSS®E power system assessment.
Home-page: https://
Author: Varchas Solutions Pty Ltd
Author-email: Pritesh Patel <pritesh.patel@varchassolutions.com.au>
License: Proprietary
Requires-Python: >=3.9,<3.13
License-File: LICENSE
Requires-Dist: pillow>=11.2.1
Requires-Dist: pymupdf>=1.26.3
Requires-Dist: matplotlib>=3.9.4
Requires-Dist: numpy>=2.0.2
Requires-Dist: pandas>=2.3.1
Requires-Dist: openpyxl>=3.1.5
Requires-Dist: requests>=2.32.4
Requires-Dist: scipy>=1.13.1
Requires-Dist: python-dotenv>=1.1.1
Dynamic: author
Dynamic: home-page
Dynamic: license-file
Dynamic: requires-python
